matchit/__init__.py
matchit/__init__.pyi
matchit/matchit.abi3.so
matchit/py.typed
matchit.libs/libgcc_s-f685abf1.so.1
python_matchit-0.3.0.dist-info/METADATA
python_matchit-0.3.0.dist-info/WHEEL
python_matchit-0.3.0.dist-info/RECORD
