Metadata-Version: 2.4
Name: python-matchit
Version: 0.3.0
Classifier: Programming Language :: Rust
Classifier: Programming Language :: Python :: Implementation :: CPython
Classifier: Programming Language :: Python :: Implementation :: PyPy
Summary: Bindings for matchit rust library.
Requires-Python: >=3.8
